{
  "legislative_session": "104th",
  "identifier": "HR522",
  "title": "CONGRATS-LOIS CALLAHAN",
  "from_organization": "~{\"classification\": \"lower\"}",
  "classification": [
    "resolution"
  ],
  "subject": [],
  "abstracts": [
    {
      "note": "",
      "abstract": "Congratulates Lois Callahan on her election to the office of National President of the Veterans of Foreign Wars of the United States (VFW) Auxiliary, serving from 2025-2026."
    }
  ],
  "other_titles": [],
  "other_identifiers": [],
  "actions": [
    {
      "description": "Filed with the Clerk by Rep. Stephanie A. Kifowit",
      "date": "2025-10-22",
      "organization_id": "~{\"classification\": \"lower\"}",
      "classification": [
        "filing"
      ],
      "related_entities": [],
      "_processing": {
        "log_file_created": "2025-10-24T05:19:55Z"
      }
    }
  ],
  "sponsorships": [
    {
      "name": "Stephanie A. Kifowit",
      "classification": "primary",
      "entity_type": "person",
      "primary": true,
      "person_id": "~{\"chamber\": \"lower\", \"name\": \"Stephanie A. Kifowit\"}",
      "organization_id": null
    }
  ],
  "related_bills": [],
  "versions": [
    {
      "note": "Introduced",
      "links": [
        {
          "url": "https://ilga.gov/documents/legislation/104/HR/PDF/10400HR0522.pdf",
          "media_type": "application/pdf"
        },
        {
          "url": "https://ilga.gov/Legislation/BillStatus/FullText?LegDocId=205760&DocName=10400HR0522&DocNum=522&DocTypeID=HR&LegID=164461&GAID=18&SessionID=114&SpecSess=&Session=&Print=1",
          "media_type": "text/html"
        }
      ],
      "date": "",
      "classification": ""
    }
  ],
  "documents": [],
  "citations": [],
  "sources": [
    {
      "url": "https://ilga.gov/Legislation/BillStatus?DocNum=522&GAID=18&DocTypeID=HR&LegId=164461&SessionID=114",
      "note": ""
    }
  ],
  "extras": {},
  "jurisdiction": {
    "id": "ocd-jurisdiction/country:us/state:il/government",
    "name": "Illinois",
    "classification": "state",
    "division_id": "ocd-division/country:us/state:il"
  },
  "_processing": {
    "logs_latest_update": "2025-10-24T05:19:55Z"
  }
}