{
  "legislative_session": "104th",
  "identifier": "SR235",
  "title": "ANIMAL WELFARE DAY",
  "from_organization": "~{\"classification\": \"upper\"}",
  "classification": [
    "resolution"
  ],
  "subject": [],
  "abstracts": [
    {
      "note": "",
      "abstract": "Declares April 23, 2026 as Animal Welfare Day in the State of Illinois to reflect on the importance of just and humane treatment of animals. Discourages all acts of bovine tailing and its associated harms."
    }
  ],
  "other_titles": [],
  "other_identifiers": [],
  "actions": [
    {
      "description": "Filed with Secretary",
      "date": "2025-04-23",
      "organization_id": "~{\"classification\": \"upper\"}",
      "classification": [
        "filing"
      ],
      "related_entities": [],
      "_processing": {
        "log_file_created": "2025-10-24T05:19:53Z"
      }
    },
    {
      "description": "Referred to Assignments",
      "date": "2025-04-23",
      "organization_id": "~{\"classification\": \"upper\"}",
      "classification": [],
      "related_entities": [],
      "_processing": {
        "log_file_created": "2025-10-24T05:19:53Z"
      }
    },
    {
      "description": "Approved for Consideration Assignments",
      "date": "2025-05-27",
      "organization_id": "~{\"classification\": \"upper\"}",
      "classification": [],
      "related_entities": [],
      "_processing": {
        "log_file_created": "2025-10-24T05:19:53Z"
      }
    },
    {
      "description": "Placed on Calendar Order of Secretary's Desk Resolutions May 28, 2025",
      "date": "2025-05-27",
      "organization_id": "~{\"classification\": \"upper\"}",
      "classification": [],
      "related_entities": [],
      "_processing": {
        "log_file_created": "2025-10-24T05:19:53Z"
      }
    },
    {
      "description": "Pursuant to Senate Rule 3-9(b) / Referred to Assignments",
      "date": "2025-07-02",
      "organization_id": "~{\"classification\": \"upper\"}",
      "classification": [],
      "related_entities": [],
      "_processing": {
        "log_file_created": "2025-10-24T05:19:53Z"
      }
    },
    {
      "description": "Approved for Consideration Assignments",
      "date": "2025-10-14",
      "organization_id": "~{\"classification\": \"upper\"}",
      "classification": [],
      "related_entities": [],
      "_processing": {
        "log_file_created": "2025-10-24T05:19:53Z"
      }
    },
    {
      "description": "Placed on Calendar Order of Secretary's Desk Resolutions October 15, 2025",
      "date": "2025-10-14",
      "organization_id": "~{\"classification\": \"upper\"}",
      "classification": [],
      "related_entities": [],
      "_processing": {
        "log_file_created": "2025-10-24T05:19:53Z"
      }
    },
    {
      "description": "Resolution Adopted",
      "date": "2025-10-15",
      "organization_id": "~{\"classification\": \"upper\"}",
      "classification": [
        "passage"
      ],
      "related_entities": [],
      "_processing": {
        "log_file_created": "2025-10-24T05:19:53Z"
      }
    },
    {
      "description": "Added as Co-Sponsor Sen. Dave Syverson",
      "date": "2025-10-15",
      "organization_id": "~{\"classification\": \"upper\"}",
      "classification": [],
      "related_entities": [],
      "_processing": {
        "log_file_created": "2025-10-24T05:19:53Z"
      }
    },
    {
      "description": "Added as Co-Sponsor Sen. Graciela Guzm\u00e1n",
      "date": "2025-10-15",
      "organization_id": "~{\"classification\": \"upper\"}",
      "classification": [],
      "related_entities": [],
      "_processing": {
        "log_file_created": "2025-10-24T05:19:53Z"
      }
    },
    {
      "description": "Added as Co-Sponsor Sen. Li Arellano, Jr.",
      "date": "2025-10-15",
      "organization_id": "~{\"classification\": \"upper\"}",
      "classification": [],
      "related_entities": [],
      "_processing": {
        "log_file_created": "2025-10-24T05:19:53Z"
      }
    }
  ],
  "sponsorships": [
    {
      "name": "Rachel Ventura",
      "classification": "primary",
      "entity_type": "person",
      "primary": true,
      "person_id": "~{\"chamber\": \"upper\", \"name\": \"Rachel Ventura\"}",
      "organization_id": null
    },
    {
      "name": "Dave Syverson",
      "classification": "cosponsor",
      "entity_type": "person",
      "primary": false,
      "person_id": "~{\"chamber\": \"upper\", \"name\": \"Dave Syverson\"}",
      "organization_id": null
    },
    {
      "name": "Graciela Guzm\u00e1n",
      "classification": "cosponsor",
      "entity_type": "person",
      "primary": false,
      "person_id": "~{\"chamber\": \"upper\", \"name\": \"Graciela Guzm\\u00e1n\"}",
      "organization_id": null
    },
    {
      "name": "Li Arellano, Jr.",
      "classification": "cosponsor",
      "entity_type": "person",
      "primary": false,
      "person_id": "~{\"chamber\": \"upper\", \"name\": \"Li Arellano, Jr.\"}",
      "organization_id": null
    }
  ],
  "related_bills": [],
  "versions": [
    {
      "note": "Introduced",
      "links": [
        {
          "url": "https://ilga.gov/documents/legislation/104/SR/PDF/10400SR0235.pdf",
          "media_type": "application/pdf"
        },
        {
          "url": "https://ilga.gov/Legislation/BillStatus/FullText?LegDocId=204375&DocName=10400SR0235&DocNum=235&DocTypeID=SR&LegID=163516&GAID=18&SessionID=114&SpecSess=&Session=&Print=1",
          "media_type": "text/html"
        }
      ],
      "date": "",
      "classification": ""
    }
  ],
  "documents": [],
  "citations": [],
  "sources": [
    {
      "url": "https://ilga.gov/Legislation/BillStatus?DocNum=235&GAID=18&DocTypeID=SR&LegId=163516&SessionID=114",
      "note": ""
    }
  ],
  "extras": {},
  "jurisdiction": {
    "id": "ocd-jurisdiction/country:us/state:il/government",
    "name": "Illinois",
    "classification": "state",
    "division_id": "ocd-division/country:us/state:il"
  },
  "_processing": {
    "logs_latest_update": "2025-10-24T05:19:53Z",
    "text_extraction_latest_update": "2025-10-24T20:58:04.582089Z"
  }
}